jira_dump/__init__.py
jira_dump/base.py
jira_dump/helpers/__init__.py
jira_dumper-0.1.0.dist-info/LICENSE
jira_dumper-0.1.0.dist-info/METADATA
jira_dumper-0.1.0.dist-info/WHEEL
jira_dumper-0.1.0.dist-info/top_level.txt
jira_dumper-0.1.0.dist-info/RECORD
